PyLinearSolver/IterativeSolvers.py
PyLinearSolver/__init__.py
PyLinearSolver/main.py
PyLinearSolver-0.1.4.data/data/LICENSE
PyLinearSolver-0.1.4.dist-info/LICENSE
PyLinearSolver-0.1.4.dist-info/METADATA
PyLinearSolver-0.1.4.dist-info/WHEEL
PyLinearSolver-0.1.4.dist-info/top_level.txt
PyLinearSolver-0.1.4.dist-info/RECORD
