Metadata-Version: 2.1
Name: PyLinearSolver
Version: 0.1.4
Summary: A python interface package for many well known linear solvers libraries in many languages, Julia, C++, etc...
Home-page: https://github.com/AhmedMagdyHendawy/PyLinearSolver
Author: Ahmed Hendawy, Bernhard Rolle
Author-email: ahmedmagdyahmed1996@outlook.com
License: UNKNOWN
Project-URL: Documentation, https://pylinearsolver.readthedocs.io/en/latest/index.html
Project-URL: Source Code, https://github.com/AhmedMagdyHendawy/PyLinearSolver
Platform: UNKNOWN
Requires-Dist: numpy
Requires-Dist: julia
Requires-Dist: PyLinearSolver
